[
    {
        "group": "Recommended",
        "items": [
            "jujutsuKaisen",
            "chainsawMan",
            "tensura"
        ],
        "title": [
            "Jujutsu Kaisen",
            "Chainsaw Man",
            "That Time I got Reincarnated As A Slime"
        ],
        "links": [
            "manga/shonen/Jujutsu Kaisen",
            "manga/shonen/Chainsaw Man",
            "manga/shonen/Tensura"
        ]
    },
    {
        "group": "Shonen",
        "items": [
            "chainsawMan",
            "jujutsuKaisen",
            "tensura"
        ],
        "title": [
            "Chainsaw Man",
            "Jujutsu Kaisen",
            "That Time I got Reincarnated As A Slime"
        ],
        "links": [
            "manga/shonen/Chainsaw Man",
            "manga/shonen/Jujutsu Kaisen",
            "manga/shonen/Tensura"
        ]
    }
]